Metadata-Version: 1.0
Name: prob-s-dists
Version: 0.3
Summary: Gaussian distribution, Binomial distribution
Home-page: UNKNOWN
Author: Saswata Mishra
Author-email: mysaswatamishra@gmail.com
License: UNKNOWN
Platform: UNKNOWN
